qtalib/__init__.py
qtalib/indicators.cpython-38-darwin.so
qtalib/indicators.pyx
qtalib/py_indicators.py
qtalib/setup.py
qtalib/util.cpython-38-darwin.so
qtalib/util.pyx
qtalib-0.0.2.dist-info/METADATA
qtalib-0.0.2.dist-info/WHEEL
qtalib-0.0.2.dist-info/entry_points.txt
qtalib-0.0.2.dist-info/top_level.txt
qtalib-0.0.2.dist-info/RECORD
