Metadata-Version: 2.1
Name: qtalib
Version: 0.0.2
Summary: QTALIB: Quantitative Technical Analysis Library
Home-page: 
Author: josephchen
Author-email: josephchenhk@gmail.com
License: JXW
Keywords: Quantitative Trading,Technical Analysis,QTaLib
Platform: any
Requires-Dist: finta
Requires-Dist: pandas
Requires-Dist: numpy
Requires-Dist: Cython
